[
    {
        "dataset": "REDD_multilabel",
        "house_no": "3",
        "win_size": 60,
        "bit_string": "010000010101010110110000101000000100010100111100111011101101101010100100101001",
        "out_channels": [
            32,
            32,
            64
        ]
    },
    {
        "dataset": "REDD_multilabel",
        "house_no": "3",
        "win_size": 150,
        "bit_string": "111000101010110101111101011010111110000001011111101011101101110010101100001010",
        "out_channels": [
            64,
            64,
            64
        ]
    },
    {
        "dataset": "REDD_multilabel",
        "house_no": "3",
        "win_size": 300,
        "bit_string": "101010101001010010110010101010111100000011011100110011101101110010101100001011",
        "out_channels": [
            32,
            64,
            64
        ]
    }
]