[
    {
        "dataset": "REDD_multilabel",
        "house_no": 1,
        "win_size": 60,
        "bit_string": "101010101001010010100100011000000010101100011101010001000111110010111011001010",
        "out_channels": [
            32,
            64,
            64
        ]
    },
    {
        "dataset": "REDD_multilabel",
        "house_no": 1,
        "win_size": 60,
        "bit_string": "111000001000111010110100011000011000011011100101110100101101000001001101011100",
        "out_channels": [
            32,
            32,
            64
        ]
    },
    {
        "dataset": "REDD_multilabel",
        "house_no": 1,
        "win_size": 60,
        "bit_string": "111001101001011001111000110100111010111101101011101011101011110110000011110001",
        "out_channels": [
            32,
            32,
            32
        ]
    },
    {
        "dataset": "REDD_multilabel",
        "house_no": 1,
        "win_size": 60,
        "bit_string": "111000001000111110110100011000011000011011100101110100100101001110011100011100",
        "out_channels": [
            32,
            32,
            64
        ]
    },
    {
        "dataset": "REDD_multilabel",
        "house_no": 1,
        "win_size": 60,
        "bit_string": "111000000000101101101001111111001110001010010010111110010010000110011100011100",
        "out_channels": [
            32,
            32,
            64
        ]
    },
    {
        "dataset": "REDD_multilabel",
        "house_no": 1,
        "win_size": 60,
        "bit_string": "111000001001011001111010110100011000010010100101110100001000010010011010100001",
        "out_channels": [
            32,
            32,
            32
        ]
    },
    {
        "dataset": "REDD_multilabel",
        "house_no": 1,
        "win_size": 60,
        "bit_string": "101001100101010101110100111000011010011010011010010100110010000110011100010010",
        "out_channels": [
            32,
            32,
            32
        ]
    },
    {
        "dataset": "REDD_multilabel",
        "house_no": 1,
        "win_size": 60,
        "bit_string": "111000001001011001111010110100011000011010100101110100101000000010011011100001",
        "out_channels": [
            32,
            32,
            32
        ]
    },
    {
        "dataset": "REDD_multilabel",
        "house_no": 1,
        "win_size": 60,
        "bit_string": "111001001000111010110100110000011000011111110111110100111010000110011011110001",
        "out_channels": [
            32,
            32,
            32
        ]
    },
    {
        "dataset": "REDD_multilabel",
        "house_no": 1,
        "win_size": 60,
        "bit_string": "111000000001100110110100110101011000010010100001111010010010001110110001100000",
        "out_channels": [
            32,
            32,
            32
        ]
    },
    {
        "dataset": "REDD_multilabel",
        "house_no": 1,
        "win_size": 60,
        "bit_string": "110000000000100100110100011000010010001101101011101000010110101110110011100001",
        "out_channels": [
            32,
            32,
            32
        ]
    },
    {
        "dataset": "REDD_multilabel",
        "house_no": 1,
        "win_size": 150,
        "bit_string": "111101101100100010100101010111100100011100001100110111111001011111110000100100",
        "out_channels": [
            32,
            64,
            64
        ]
    },
    {
        "dataset": "REDD_multilabel",
        "house_no": 1,
        "win_size": 150,
        "bit_string": "101010101101010010100100011000000101111100001100111011101101110010101100001010",
        "out_channels": [
            32,
            64,
            64
        ]
    },
    {
        "dataset": "REDD_multilabel",
        "house_no": 1,
        "win_size": 150,
        "bit_string": "101010101001010010100100011000000100010100111100111011101101110010101100001010",
        "out_channels": [
            32,
            64,
            64
        ]
    },
    {
        "dataset": "REDD_multilabel",
        "house_no": 1,
        "win_size": 150,
        "bit_string": "110110101001010101110101000111001010101111111011101000011110100010011111110000",
        "out_channels": [
            32,
            64,
            64
        ]
    },
    {
        "dataset": "REDD_multilabel",
        "house_no": 1,
        "win_size": 150,
        "bit_string": "101000001011001010000010100111110011111100001100000101000111111001100101000101",
        "out_channels": [
            32,
            32,
            64
        ]
    },
    {
        "dataset": "REDD_multilabel",
        "house_no": 1,
        "win_size": 150,
        "bit_string": "011000100101010001101000011000000100010100111100111011101101110001011010101111",
        "out_channels": [
            32,
            32,
            64
        ]
    },
    {
        "dataset": "REDD_multilabel",
        "house_no": 1,
        "win_size": 150,
        "bit_string": "011000100101010001101000011000000100010100111100111011101101110011011010101111",
        "out_channels": [
            32,
            32,
            64
        ]
    },
    {
        "dataset": "REDD_multilabel",
        "house_no": 1,
        "win_size": 150,
        "bit_string": "101100000010100101001101000101010100011100001001010111011100101010111100001010",
        "out_channels": [
            32,
            32,
            64
        ]
    },
    {
        "dataset": "REDD_multilabel",
        "house_no": 1,
        "win_size": 150,
        "bit_string": "100000100101010101101001111111001110001010011011111010010000100101011110101111",
        "out_channels": [
            32,
            32,
            64
        ]
    },
    {
        "dataset": "REDD_multilabel",
        "house_no": 1,
        "win_size": 150,
        "bit_string": "101100000010100101001101000101010100011110001001010111011100101010111100001010",
        "out_channels": [
            32,
            32,
            64
        ]
    },
    {
        "dataset": "REDD_multilabel",
        "house_no": 1,
        "win_size": 150,
        "bit_string": "100000100001000101100010100110001110001010011011111010010000100101010110101111",
        "out_channels": [
            32,
            32,
            64
        ]
    },
    {
        "dataset": "REDD_multilabel",
        "house_no": 1,
        "win_size": 150,
        "bit_string": "100000100101000101000100101000100100110100111001111010010000000101010110101111",
        "out_channels": [
            32,
            32,
            64
        ]
    },
    {
        "dataset": "REDD_multilabel",
        "house_no": 1,
        "win_size": 150,
        "bit_string": "010001001100100101000001111100000100101110001100111001000111110010100101000001",
        "out_channels": [
            32,
            32,
            32
        ]
    },
    {
        "dataset": "REDD_multilabel",
        "house_no": 1,
        "win_size": 150,
        "bit_string": "010001000010100101100101111110000100011100111100110101000111110010101101000001",
        "out_channels": [
            32,
            32,
            32
        ]
    },
    {
        "dataset": "REDD_multilabel",
        "house_no": 1,
        "win_size": 150,
        "bit_string": "010001000010100101100101111100000100010100111100110001000111110010100101000001",
        "out_channels": [
            32,
            32,
            32
        ]
    },
    {
        "dataset": "REDD_multilabel",
        "house_no": 1,
        "win_size": 150,
        "bit_string": "010001000010100101100101111100000100011100111100110001000111110010101101000001",
        "out_channels": [
            32,
            32,
            32
        ]
    },
    {
        "dataset": "REDD_multilabel",
        "house_no": 1,
        "win_size": 150,
        "bit_string": "010000000010101101100100011011001010101100010011111001000011110010100101010000",
        "out_channels": [
            32,
            32,
            32
        ]
    },
    {
        "dataset": "REDD_multilabel",
        "house_no": 1,
        "win_size": 150,
        "bit_string": "010001000000100101100101111100000100010100111100110001000111110010100101000001",
        "out_channels": [
            32,
            32,
            32
        ]
    },
    {
        "dataset": "REDD_multilabel",
        "house_no": 1,
        "win_size": 150,
        "bit_string": "010000000010100101101000011001000100011100010011110001000000100100100101010100",
        "out_channels": [
            32,
            32,
            32
        ]
    },
    {
        "dataset": "REDD_multilabel",
        "house_no": 1,
        "win_size": 150,
        "bit_string": "010000000010100101101000011001000100001100010011110001000000100100100101010100",
        "out_channels": [
            32,
            32,
            32
        ]
    },
    {
        "dataset": "REDD_multilabel",
        "house_no": 1,
        "win_size": 300,
        "bit_string": "101000010001010101100111000110010111011001000010101010010000100101010100011100",
        "out_channels": [
            32,
            64,
            64
        ]
    },
    {
        "dataset": "REDD_multilabel",
        "house_no": 1,
        "win_size": 300,
        "bit_string": "100000001001010010010010001100111001111010011011011010010001100101011110101111",
        "out_channels": [
            32,
            32,
            64
        ]
    },
    {
        "dataset": "REDD_multilabel",
        "house_no": 1,
        "win_size": 300,
        "bit_string": "100000101001010010000100101100000110001010011011111010111011011110010100011110",
        "out_channels": [
            32,
            32,
            64
        ]
    },
    {
        "dataset": "REDD_multilabel",
        "house_no": 1,
        "win_size": 300,
        "bit_string": "100000100101111101101001100110000101010001000010111000010000100101110010101101",
        "out_channels": [
            32,
            32,
            64
        ]
    },
    {
        "dataset": "REDD_multilabel",
        "house_no": 1,
        "win_size": 300,
        "bit_string": "100000100001010111100100001100110000000011111011111010110000101100011110111111",
        "out_channels": [
            32,
            32,
            64
        ]
    },
    {
        "dataset": "REDD_multilabel",
        "house_no": 1,
        "win_size": 300,
        "bit_string": "100000100001010111100100101100111000001011110011111010110000101101011110111111",
        "out_channels": [
            32,
            32,
            64
        ]
    },
    {
        "dataset": "REDD_multilabel",
        "house_no": 1,
        "win_size": 300,
        "bit_string": "100000100001010111100100101100111000001011110011111010110000101100011110111111",
        "out_channels": [
            32,
            32,
            64
        ]
    },
    {
        "dataset": "REDD_multilabel",
        "house_no": 1,
        "win_size": 300,
        "bit_string": "100000100001010111100100100101000010000001110011111010010010100101011110101111",
        "out_channels": [
            32,
            32,
            32
        ]
    },
    {
        "dataset": "REDD_multilabel",
        "house_no": 1,
        "win_size": 300,
        "bit_string": "100000000000000101000111100100100011001011100100011110110101100010101010000011",
        "out_channels": [
            32,
            32,
            32
        ]
    }
]